[{"keyword": "Feature", "uri": "/Users/matthewchadwell/PycharmProjects/examp_sel/tests/features/home_page.feature", "name": "Homepage image shown", "id": "/users/matthewchadwell/pycharmprojects/examp_sel/tests/features/home_page.feature", "line": 1, "description": "As a user when I enter url the\nproduct image should show", "tags": [], "elements": [{"keyword": "Scenario", "id": "test_hp", "name": "Access homepage and view product image", "line": 8, "description": "", "tags": [], "type": "scenario", "steps": [{"keyword": "Then", "name": "The game image should be shown", "line": 10, "match": {"location": ""}, "result": {"status": "passed", "duration": 223733200}}]}]}]